worldguard_api/__init__.py
worldguard_api/models.py
worldguard_api-0.0.2.dist-info/LICENSE
worldguard_api-0.0.2.dist-info/METADATA
worldguard_api-0.0.2.dist-info/WHEEL
worldguard_api-0.0.2.dist-info/top_level.txt
worldguard_api-0.0.2.dist-info/RECORD
