Metadata-Version: 2.1
Name: worldguard-api
Version: 0.0.2
Summary: Minecraft WorldGuard API
Home-page: https://git.cofob.ru/cofob/worldguard_api
License: UNKNOWN
Platform: UNKNOWN
Requires-Python: >=3.6
License-File: LICENSE
Requires-Dist: mysql-connector-python
